LICENSE.txt
MANIFEST.in
README.md
pyproject.toml
setup.cfg
setup.py
include/a/a.h
include/a/avl.h
include/a/buf.h
include/a/complex.h
include/a/crc.h
include/a/fuzzy.h
include/a/hpf.h
include/a/list.h
include/a/lpf.h
include/a/math.h
include/a/mf.h
include/a/notefreqs.h
include/a/pid.h
include/a/pid_fuzzy.h
include/a/pid_neuro.h
include/a/poly.h
include/a/que.h
include/a/rbt.h
include/a/regress.h
include/a/regress_linear.h
include/a/regress_simple.h
include/a/slist.h
include/a/str.h
include/a/tf.h
include/a/trajbell.h
include/a/trajpoly3.h
include/a/trajpoly5.h
include/a/trajpoly7.h
include/a/trajtrap.h
include/a/utf.h
include/a/vec.h
include/a/version.h
python/liba.pyi
python/liba.egg-info/PKG-INFO
python/liba.egg-info/SOURCES.txt
python/liba.egg-info/dependency_links.txt
python/liba.egg-info/top_level.txt
python/src/liba.c
python/src/liba.pyx
python/src/a/__init__.pxd
python/src/a/crc.pxd
python/src/a/fuzzy.pxd
python/src/a/hpf.pxd
python/src/a/lpf.pxd
python/src/a/math.pxd
python/src/a/mf.pxd
python/src/a/pid.pxd
python/src/a/pid_fuzzy.pxd
python/src/a/pid_neuro.pxd
python/src/a/poly.pxd
python/src/a/regress_simple.pxd
python/src/a/tf.pxd
python/src/a/trajbell.pxd
python/src/a/trajpoly3.pxd
python/src/a/trajpoly5.pxd
python/src/a/trajpoly7.pxd
python/src/a/trajtrap.pxd
python/src/a/version.pxd
src/a.c
src/avl.c
src/buf.c
src/complex.c
src/crc.c
src/fuzzy.c
src/math.c
src/mf.c
src/pid.c
src/pid_fuzzy.c
src/pid_neuro.c
src/poly.c
src/que.c
src/rbt.c
src/regress.c
src/regress_linear.c
src/regress_simple.c
src/str.c
src/tf.c
src/trajbell.c
src/trajpoly3.c
src/trajpoly5.c
src/trajpoly7.c
src/trajtrap.c
src/utf.c
src/vec.c
src/version.c