Metadata-Version: 2.1
Name: liba
Version: 0.1.15
Summary: An algorithm library based on C/C++
Home-page: https://github.com/tqfx/liba
Author: tqfx
Author-email: tqfx@tqfx.org
License: MPL-2.0
Keywords: algorithms
Platform: CPython
Classifier: Programming Language :: C
Classifier: Programming Language :: C++
Classifier: Programming Language :: Cython
Classifier: Programming Language :: Python
Classifier: License :: OSI Approved :: Mozilla Public License 2.0 (MPL 2.0)
License-File: LICENSE.txt
